amd_hipdf/__init__.py
amd_hipdf-0.0.2.dist-info/METADATA
amd_hipdf-0.0.2.dist-info/WHEEL
amd_hipdf-0.0.2.dist-info/top_level.txt
amd_hipdf-0.0.2.dist-info/RECORD
