Metadata-Version: 2.4
Name: amd-hipdf
Version: 0.0.2
Summary: hipDF - GPU Dataframe for AMD GPUs
Author-email: AMD <support@amd.com>
License: Apache 2.0 AND MIT
Project-URL: Homepage, https://github.com/rocm/hipdf
Requires-Python: >=3.8
